yolov8_onnx/__init__.py
yolov8_onnx/main.py
yolov8_onnx/centers/__init__.py
yolov8_onnx/centers/engines.py
yolov8_onnx/centers/utils.py
yolov8_onnx-1.0.4.dist-info/LICENSE
yolov8_onnx-1.0.4.dist-info/METADATA
yolov8_onnx-1.0.4.dist-info/WHEEL
yolov8_onnx-1.0.4.dist-info/top_level.txt
yolov8_onnx-1.0.4.dist-info/RECORD
