Metadata-Version: 2.1
Name: yolov8-onnx
Version: 1.0.4
Summary: YoloV8 Package Tools
Author: LauNT
Author-email: ttruongllau@gmail.com
License: Apache License 2.0
Requires-Python: >=3.7
License-File: LICENSE
Requires-Dist: onnxruntime
Requires-Dist: numpy
Requires-Dist: opencv-python
